python/__init__.py
tormenta20-0.1.0.dist-info/LICENSE.txt
tormenta20-0.1.0.dist-info/METADATA
tormenta20-0.1.0.dist-info/WHEEL
tormenta20-0.1.0.dist-info/top_level.txt
tormenta20-0.1.0.dist-info/RECORD
