Metadata-Version: 2.1
Name: tormenta20
Version: 0.1.0
Summary: A Ruby, Node and Python library with data about the Brazilian TTRPG, Tormenta20
Author-email: LuanGB <luan.goncbs@gmail.com>
Project-URL: Homepage, https://github.com/LuanGB/tormenta20
Project-URL: Issues, https://github.com/LuanGB/tormenta20/issues
Classifier: Programming Language :: Python :: 3
Classifier: License :: OSI Approved :: MIT License
Classifier: Operating System :: OS Independent
Requires-Python: >=3.8
License-File: LICENSE.txt
